zaishiyishihejipage/__init__.py
zaishiyishihejipage/data/main/content/再试一试目录.html
zaishiyishihejipage/data/main/content/再试一试请再来一次目录.html
zaishiyishihejipage/data/main/content/再试一试请继续目录.html
zaishiyishihejipage/data/main/content/凡圣名录.html
zaishiyishihejipage/data/main/display/三盏灯.html
zaishiyishihejipage/data/main/display/四大虾客.html
zaishiyishihejipage/data/main/display/烛明和睛明的家.html
zaishiyishihejipage/data/main/passage/三朵鲜花（10）.html
zaishiyishihejipage/data/main/passage/三朵鲜花（1）.html
zaishiyishihejipage/data/main/passage/三朵鲜花（2）.html
zaishiyishihejipage/data/main/passage/三朵鲜花（3）.html
zaishiyishihejipage/data/main/passage/三朵鲜花（4）.html
zaishiyishihejipage/data/main/passage/三朵鲜花（5）.html
zaishiyishihejipage/data/main/passage/三朵鲜花（6）.html
zaishiyishihejipage/data/main/passage/三朵鲜花（7）.html
zaishiyishihejipage/data/main/passage/三朵鲜花（8）.html
zaishiyishihejipage/data/main/passage/三朵鲜花（9）.html
zaishiyishihejipage/data/main/passage/仪矩之行（10）.html
zaishiyishihejipage/data/main/passage/仪矩之行（1）.html
zaishiyishihejipage/data/main/passage/仪矩之行（2）.html
zaishiyishihejipage/data/main/passage/仪矩之行（3）.html
zaishiyishihejipage/data/main/passage/仪矩之行（4）.html
zaishiyishihejipage/data/main/passage/仪矩之行（5）.html
zaishiyishihejipage/data/main/passage/仪矩之行（6）.html
zaishiyishihejipage/data/main/passage/仪矩之行（7）.html
zaishiyishihejipage/data/main/passage/仪矩之行（8）.html
zaishiyishihejipage/data/main/passage/仪矩之行（9）.html
zaishiyishihejipage/data/main/passage/再试一试请再来一次（10）.html
zaishiyishihejipage/data/main/passage/再试一试请再来一次（11）.html
zaishiyishihejipage/data/main/passage/再试一试请再来一次（12）.html
zaishiyishihejipage/data/main/passage/再试一试请再来一次（13）.html
zaishiyishihejipage/data/main/passage/再试一试请再来一次（14）.html
zaishiyishihejipage/data/main/passage/再试一试请再来一次（15）.html
zaishiyishihejipage/data/main/passage/再试一试请再来一次（16）.html
zaishiyishihejipage/data/main/passage/再试一试请再来一次（17）.html
zaishiyishihejipage/data/main/passage/再试一试请再来一次（18）.html
zaishiyishihejipage/data/main/passage/再试一试请再来一次（19）.html
zaishiyishihejipage-0.0.2.dist-info/licenses/LICENSE
zaishiyishihejipage-0.0.2.dist-info/METADATA
zaishiyishihejipage-0.0.2.dist-info/WHEEL
zaishiyishihejipage-0.0.2.dist-info/top_level.txt
zaishiyishihejipage-0.0.2.dist-info/RECORD
