Metadata-Version: 2.4
Name: zaishiyishihejipage
Version: 0.0.2
Summary: 一个存储王梓明做的网页的包
Home-page: 
Author: 王梓明
Author-email: 1272660211@qq.com
Classifier: Programming Language :: Python :: 3
Classifier: Operating System :: OS Independent
License-File: LICENSE
Dynamic: author
Dynamic: author-email
Dynamic: classifier
Dynamic: description
Dynamic: description-content-type
Dynamic: license-file
Dynamic: summary
